odoo/addons/hr_professional_category/README.rst
odoo/addons/hr_professional_category/__init__.py
odoo/addons/hr_professional_category/__manifest__.py
odoo/addons/hr_professional_category/demo/hr_professional_category_demo.xml
odoo/addons/hr_professional_category/i18n/es.po
odoo/addons/hr_professional_category/i18n/hr_professional_category.pot
odoo/addons/hr_professional_category/i18n/it.po
odoo/addons/hr_professional_category/models/__init__.py
odoo/addons/hr_professional_category/models/hr_contract.py
odoo/addons/hr_professional_category/models/hr_professional_category.py
odoo/addons/hr_professional_category/readme/CONFIGURE.md
odoo/addons/hr_professional_category/readme/CONTRIBUTORS.md
odoo/addons/hr_professional_category/readme/DESCRIPTION.md
odoo/addons/hr_professional_category/readme/USAGE.md
odoo/addons/hr_professional_category/security/ir.model.access.csv
odoo/addons/hr_professional_category/security/security.xml
odoo/addons/hr_professional_category/static/description/icon.png
odoo/addons/hr_professional_category/static/description/index.html
odoo/addons/hr_professional_category/tests/__init__.py
odoo/addons/hr_professional_category/tests/test_hr_professional_category.py
odoo/addons/hr_professional_category/views/hr_contract_views.xml
odoo/addons/hr_professional_category/views/hr_professional_category_views.xml
odoo_addon_hr_professional_category-18.0.1.0.0.2.dist-info/METADATA
odoo_addon_hr_professional_category-18.0.1.0.0.2.dist-info/WHEEL
odoo_addon_hr_professional_category-18.0.1.0.0.2.dist-info/top_level.txt
odoo_addon_hr_professional_category-18.0.1.0.0.2.dist-info/RECORD
